blitz_js_query/__init__.py
blitz_js_query/auth.py
blitz_js_query/blitz_queue.py
blitz_js_query/connection.py
blitz_js_query/helpers.py
blitz_js_query/tests/__init__.py
blitz_js_query/tests/test_http.py
blitz_js_query-0.1.3.dist-info/DESCRIPTION.rst
blitz_js_query-0.1.3.dist-info/METADATA
blitz_js_query-0.1.3.dist-info/RECORD
blitz_js_query-0.1.3.dist-info/WHEEL
blitz_js_query-0.1.3.dist-info/metadata.json
blitz_js_query-0.1.3.dist-info/top_level.txt
