Metadata-Version: 2.0
Name: blitz-js-query
Version: 0.1.3
Summary: HTTP/Socket.io adapter for the blitz.js framework
Home-page: https://github.com/nexus-devs/pip-blitz-query
Author: Nexus Devs
Author-email: nexus@nexus-stats.com
License: MIT
Keywords: development blitz nexus socket.io http
Platform: UNKNOWN
Classifier: Development Status :: 3 - Alpha
Classifier: Intended Audience :: Developers
Classifier: Topic :: Internet :: WWW/HTTP
Classifier: License :: OSI Approved :: MIT License
Classifier: Programming Language :: Python :: 3
Classifier: Programming Language :: Python :: 3.3
Classifier: Programming Language :: Python :: 3.4
Classifier: Programming Language :: Python :: 3.5
Classifier: Programming Language :: Python :: 3.6
Requires-Dist: promise
Requires-Dist: requests
Requires-Dist: socketIO-client-nexus
